garpix_jira_pages/MANIFEST.in
garpix_jira_pages/__init__.py
garpix_jira_pages/apps.py
garpix_jira_pages/setup.py
garpix_jira_pages/__pycache__/__init__.cpython-38.pyc
garpix_jira_pages/__pycache__/apps.cpython-38.pyc
garpix_jira_pages/admin/__init__.py
garpix_jira_pages/admin/projects_worklog_table_by_days_page.py
garpix_jira_pages/admin/specialization_worklog_table_by_days_page.py
garpix_jira_pages/admin/user_project_worklog_table_by_days_page.py
garpix_jira_pages/admin/worklog_table_by_days_page.py
garpix_jira_pages/admin/__pycache__/__init__.cpython-38.pyc
garpix_jira_pages/admin/__pycache__/projects_worklog_table_by_days_page.cpython-38.pyc
garpix_jira_pages/admin/__pycache__/specialization_worklog_table_by_days_page.cpython-38.pyc
garpix_jira_pages/admin/__pycache__/user_project_worklog_table_by_days_page.cpython-38.pyc
garpix_jira_pages/admin/__pycache__/worklog_table_by_days_page.cpython-38.pyc
garpix_jira_pages/migrations/__init__.py
garpix_jira_pages/models/__init__.py
garpix_jira_pages/models/projects_worklog_table_by_days_page.py
garpix_jira_pages/models/specialization_worklog_table_by_days_page.py
garpix_jira_pages/models/user_project_worklog_table_by_days_page.py
garpix_jira_pages/models/worklog_table_by_days_page.py
garpix_jira_pages/models/__pycache__/__init__.cpython-38.pyc
garpix_jira_pages/models/__pycache__/projects_worklog_table_by_days_page.cpython-38.pyc
garpix_jira_pages/models/__pycache__/specialization_worklog_table_by_days_page.cpython-38.pyc
garpix_jira_pages/models/__pycache__/user_project_worklog_table_by_days_page.cpython-38.pyc
garpix_jira_pages/models/__pycache__/worklog_table_by_days_page.cpython-38.pyc
garpix_jira_pages/templates/garpix_jira/include/economic_css.html
garpix_jira_pages/templates/garpix_jira/include/worklog_table_cell.html
garpix_jira_pages/templates/garpix_jira/pages/projects_worklog_table_by_days.html
garpix_jira_pages/templates/garpix_jira/pages/specialization_worklog_table_by_days.html
garpix_jira_pages-1.6.0.dist-info/METADATA
garpix_jira_pages-1.6.0.dist-info/WHEEL
garpix_jira_pages-1.6.0.dist-info/top_level.txt
garpix_jira_pages-1.6.0.dist-info/RECORD
