Metadata-Version: 2.1
Name: garpix-jira-pages
Version: 1.6.0
Summary: UNKNOWN
Home-page: https://github.com/garpixcms/garpix_jira
Author: Garpix LTD
Author-email: info@garpix.com
License: MIT
Platform: UNKNOWN
Classifier: Development Status :: 4 - Beta
Classifier: Environment :: Web Environment
Classifier: Intended Audience :: Developers
Classifier: License :: OSI Approved :: MIT License
Classifier: Operating System :: OS Independent
Classifier: Programming Language :: Python
Classifier: Framework :: Django
Classifier: Programming Language :: Python :: 3.8
Requires-Dist: garpixcms (>=2.0.2)
Requires-Dist: garpix-jira (>=1.6.0)
